nbcpu/__cli__.py
nbcpu/__init__.py
nbcpu/_version.py
nbcpu/conf/__init__.py
nbcpu/conf/about/nbcpu.yaml
nbcpu/conf/dataset/nbcpu-topic_noprior.yaml
nbcpu/conf/dataset/nbcpu-topic_prior.yaml
nbcpu/conf/dataset/nbcpu-topic_uncertainty.yaml
nbcpu/conf/dataset/nbcpu-topic_uncertainty_filtered.yaml
nbcpu/conf/fetcher/khmer.yaml
nbcpu/conf/fetcher/khmer_all.yaml
nbcpu/conf/fetcher/phnompenh.yaml
nbcpu/conf/model/nbcpu-topic_noprior.yaml
nbcpu/conf/model/nbcpu-topic_prior.yaml
nbcpu/conf/model/nbcpu-topic_uncertainty.yaml
nbcpu/conf/model/nbcpu-topic_uncertainty_filtered.yaml
nbcpu/conf/pipeline/nbcpu-datasets.yaml
nbcpu/conf/pipeline/nbcpu-datasets_noprior_filter.yaml
nbcpu/conf/pipeline/nbcpu-datasets_tokenize.yaml
nbcpu/conf/pipeline/nbcpu-datasets_uncertainty_filter.yaml
nbcpu/conf/project/nbcpu.yaml
nbcpu/conf/runner/nbcpu-topic_noprior.yaml
nbcpu/conf/runner/nbcpu-topic_prior.yaml
nbcpu/conf/runner/nbcpu-topic_uncertainty.yaml
nbcpu/conf/runner/nbcpu-topic_uncertainty_filtered.yaml
nbcpu/conf/task/nbcpu-datasets.yaml
nbcpu/conf/task/nbcpu-datasets_noprior_filter.yaml
nbcpu/conf/task/nbcpu-datasets_uncertainty_filter.yaml
nbcpu/conf/tokenizer/nbcpu.yaml
nbcpu/conf/words/nbcpu-topic.yaml
nbcpu/conf/workflow/nbcpu.yaml
nbcpu/fetcher/__init__.py
nbcpu/fetcher/base.py
nbcpu/fetcher/khmer.py
nbcpu/fetcher/phnompenh.py
nbcpu/py.typed
nbcpu/topic/__init__.py
nbcpu/topic/analysis.py
nbcpu-0.19.0.dist-info/LICENSE
nbcpu-0.19.0.dist-info/METADATA
nbcpu-0.19.0.dist-info/WHEEL
nbcpu-0.19.0.dist-info/entry_points.txt
nbcpu-0.19.0.dist-info/RECORD
