Metadata-Version: 2.1
Name: nbcpu
Version: 0.19.0
Summary: Quantifying Central Bank Policy Uncertainty in a Highly Dollarized Economy: A Topic Modeling Approach
Home-page: https://entelecheia.github.io/nbcpu
License: MIT
Author: Young Joon Lee
Author-email: entelecheia@hotmail.com
Requires-Python: >=3.9,<3.13
Classifier: License :: OSI Approved :: MIT License
Classifier: Programming Language :: Python :: 3
Classifier: Programming Language :: Python :: 3.9
Classifier: Programming Language :: Python :: 3.10
Classifier: Programming Language :: Python :: 3.11
Classifier: Programming Language :: Python :: 3.12
Requires-Dist: click (>=8.1.3,<9.0.0)
Requires-Dist: hyfi (>=1.36.3,<2.0.0)
Requires-Dist: lexikanon (>=0.6.4,<0.7.0)
Requires-Dist: thematos (>=0.14.3,<0.15.0)
Project-URL: Repository, https://github.com/entelecheia/nbcpu
